conditional_parser.py
conditional_parser-0.2.1.dist-info/METADATA
conditional_parser-0.2.1.dist-info/WHEEL
conditional_parser-0.2.1.dist-info/licenses/LICENSE
conditional_parser-0.2.1.dist-info/RECORD
