Metadata-Version: 2.4
Name: conditional-parser
Version: 0.2.1
Summary: A simple package to support conditional argument parsing.
Project-URL: Homepage, https://github.com/landoskape/conditional-parser
Author-email: Andrew Landau <andrew+tyler+landau+getridofthisanddtheplusses@gmail.com>
License-Expression: MIT
License-File: LICENSE
Keywords: argparse,cli,command-line,commandline,conditional,parser
Classifier: Development Status :: 4 - Beta
Classifier: Intended Audience :: Developers
Classifier: License :: OSI Approved :: MIT License
Classifier: Operating System :: OS Independent
Classifier: Programming Language :: Python :: 3.8
Classifier: Programming Language :: Python :: 3.9
Classifier: Programming Language :: Python :: 3.10
Classifier: Programming Language :: Python :: 3.11
Classifier: Programming Language :: Python :: 3.12
Classifier: Programming Language :: Python :: 3.13
Requires-Python: >=3.8
Provides-Extra: test
Requires-Dist: pytest-cov>=4.0.0; extra == 'test'
Requires-Dist: pytest>=7.0.0; extra == 'test'
